[
    {
        "videoId": "PV_cFx29Xz0",
        "title": "Javascript sucks and it doesn't matter",
        "speakerId": "rob-ashton",
        "keywords": [
            "javascript"
        ],
        "eventId": "devday-2012"
    },
    {
        "videoId": "kK--WKlng74",
        "title": "Yeoman Bower and Grunt - Building Modern Webapps With Ease",
        "speakerId": "shai-reznik",
        "keywords": [
            "yeoman",
            "bower",
            "grunt"
        ],
        "eventId": "gdg-tel-aviv"
    }
]